[
    {
        "key": "dbln",
        "value": "%7B%2261550622844939%22%3A%22ogPu1ipN%22%2C%22100083120051917%22%3A%22SIK3tAuS%22%7D",
        "domain": "facebook.com",
        "path": "/login/device-based/",
        "hostOnly": false,
        "creation": "2024-09-26T04:34:27.968Z",
        "lastAccessed": "2024-09-26T04:34:28.007Z"
    },
    {
        "key": "datr",
        "value": "tgrwZjI_1SlwMxmzi9OH2f-3",
        "domain": "facebook.com",
        "path": "/",
        "hostOnly": false,
        "creation": "2024-09-26T04:34:28.007Z",
        "lastAccessed": "2024-09-26T04:34:28.007Z"
    },
    {
        "key": "sb",
        "value": "tgrwZuwQlh4VeMY85jBrPqps",
        "domain": "facebook.com",
        "path": "/",
        "hostOnly": false,
        "creation": "2024-09-26T04:34:28.007Z",
        "lastAccessed": "2024-09-26T04:34:28.007Z"
    },
    {
        "key": "locale",
        "value": "en_US",
        "domain": "facebook.com",
        "path": "/",
        "hostOnly": false,
        "creation": "2024-09-26T04:34:28.007Z",
        "lastAccessed": "2024-09-26T04:34:28.007Z"
    },
    {
        "key": "vpd",
        "value": "v1%3B1169x600x1.2000000476837158",
        "domain": "facebook.com",
        "path": "/",
        "hostOnly": false,
        "creation": "2024-09-26T04:34:28.010Z",
        "lastAccessed": "2024-09-26T04:34:28.010Z"
    },
    {
        "key": "ps_l",
        "value": "1",
        "domain": "facebook.com",
        "path": "/",
        "hostOnly": false,
        "creation": "2024-09-26T04:34:28.010Z",
        "lastAccessed": "2024-09-26T04:34:28.010Z"
    },
    {
        "key": "ps_n",
        "value": "1",
        "domain": "facebook.com",
        "path": "/",
        "hostOnly": false,
        "creation": "2024-09-26T04:34:28.010Z",
        "lastAccessed": "2024-09-26T04:34:28.010Z"
    },
    {
        "key": "dpr",
        "value": "1.3193362951278687",
        "domain": "facebook.com",
        "path": "/",
        "hostOnly": false,
        "creation": "2024-09-26T04:34:28.010Z",
        "lastAccessed": "2024-09-26T04:34:28.010Z"
    },
    {
        "key": "wd",
        "value": "600x1169",
        "domain": "facebook.com",
        "path": "/",
        "hostOnly": false,
        "creation": "2024-09-26T04:34:28.010Z",
        "lastAccessed": "2024-09-26T04:34:28.010Z"
    },
    {
        "key": "c_user",
        "value": "100083120051917",
        "domain": "facebook.com",
        "path": "/",
        "hostOnly": false,
        "creation": "2024-09-26T04:34:28.011Z",
        "lastAccessed": "2024-09-26T04:34:28.012Z"
    },
    {
        "key": "xs",
        "value": "19%3A2-iaxXX08Xo51Q%3A2%3A1727286121%3A-1%3A5574",
        "domain": "facebook.com",
        "path": "/",
        "hostOnly": false,
        "creation": "2024-09-26T04:34:28.012Z",
        "lastAccessed": "2024-09-26T04:34:28.012Z"
    },
    {
        "key": "fr",
        "value": "1cpJn6pVjQPD9NrUR.AWXEjCkKxzgfmS3BVt-oflGl6BQ.Bm8Ben..AAA.0.0.Bm9Etr.AWVbUNAOKww",
        "domain": "facebook.com",
        "path": "/",
        "hostOnly": false,
        "creation": "2024-09-26T04:34:28.012Z",
        "lastAccessed": "2024-09-26T04:34:28.012Z"
    },
    {
        "key": "m_page_voice",
        "value": "100083120051917",
        "domain": "facebook.com",
        "path": "/",
        "hostOnly": false,
        "creation": "2024-09-26T04:34:28.012Z",
        "lastAccessed": "2024-09-26T04:34:28.012Z"
    },
    {
        "key": "fbl_st",
        "value": "101536536%3BT%3A28788743",
        "domain": "facebook.com",
        "path": "/",
        "hostOnly": false,
        "creation": "2024-09-26T04:34:28.012Z",
        "lastAccessed": "2024-09-26T04:34:28.012Z"
    },
    {
        "key": "wl_cbv",
        "value": "v2%3Bclient_version%3A2630%3Btimestamp%3A1727324616",
        "domain": "facebook.com",
        "path": "/",
        "hostOnly": false,
        "creation": "2024-09-26T04:34:28.012Z",
        "lastAccessed": "2024-09-26T04:34:28.012Z"
    }
]
